omniinfer_client/__init__.py
omniinfer_client/exceptions.py
omniinfer_client/omni.py
omniinfer_client/proto.py
omniinfer_client/serializer.py
omniinfer_client/settings.py
omniinfer_client/utils.py
omniinfer_client/version.py
omniinfer_client-0.3.5.dist-info/METADATA
omniinfer_client-0.3.5.dist-info/WHEEL
omniinfer_client-0.3.5.dist-info/licenses/LICENSE
omniinfer_client-0.3.5.dist-info/RECORD
