Metadata-Version: 2.1
Name: omniinfer_client
Version: 0.3.5
Summary: Omniinfer SDK for Python
Project-URL: Homepage, https://github.com/omniinfer/python-sdk
Project-URL: Bug Tracker, https://discord.gg/nzqq8UScpx
Author-email: Omniinfer <omniinfer@gmail.com>
License: MIT License
License-File: LICENSE
Classifier: License :: OSI Approved :: MIT License
Classifier: Programming Language :: Python
Classifier: Programming Language :: Python :: 3
Requires-Python: >=3.6
Requires-Dist: dataclass-wizard>=0.22.2
Requires-Dist: requests>=2.27.1
